Krypton/Binomialdistribution.py
Krypton/Gaussiandistribution.py
Krypton/Generaldistribution.py
Krypton/__init__.py
Krypton_GD-1.0.1.dist-info/LICENSE
Krypton_GD-1.0.1.dist-info/METADATA
Krypton_GD-1.0.1.dist-info/WHEEL
Krypton_GD-1.0.1.dist-info/top_level.txt
Krypton_GD-1.0.1.dist-info/RECORD
