Metadata-Version: 2.1
Name: Krypton-GD
Version: 1.0.1
Summary: A small package to add up two gaussian distributions together
Home-page: https://github.com/immu0001/Krypton
Author: Imran S M
Author-email: imran.malik01@icloud.com
License: UNKNOWN
Platform: UNKNOWN
Classifier: Programming Language :: Python :: 3
Classifier: License :: OSI Approved :: MIT License
Classifier: Operating System :: OS Independent
Requires-Python: >=3.6
